django_ratelimit3-1.0.1.dist-info/DESCRIPTION.rst
django_ratelimit3-1.0.1.dist-info/METADATA
django_ratelimit3-1.0.1.dist-info/RECORD
django_ratelimit3-1.0.1.dist-info/WHEEL
django_ratelimit3-1.0.1.dist-info/metadata.json
django_ratelimit3-1.0.1.dist-info/top_level.txt
ratelimit/__init__.py
ratelimit/decorators.py
ratelimit/exceptions.py
ratelimit/middleware.py
ratelimit/mixins.py
ratelimit/models.py
ratelimit/tests.py
ratelimit/utils.py
